setup.py
czylog/__init__.py
czylog/czylog.py
czylog.egg-info/PKG-INFO
czylog.egg-info/SOURCES.txt
czylog.egg-info/dependency_links.txt
czylog.egg-info/top_level.txt