Metadata-Version: 1.0
Name: czylog
Version: 1.0
Summary: 日志处理
Home-page: https://www.cnblogs.com/RainBol/
Author: RainBol
Author-email: 2497643794@qq.com
License: UNKNOWN
Platform: UNKNOWN
